prototype.py
setup.py
prototype.egg-info/PKG-INFO
prototype.egg-info/SOURCES.txt
prototype.egg-info/dependency_links.txt
prototype.egg-info/top_level.txt
prototype.egg-info/zip-safe