Metadata-Version: 1.0
Name: prototype
Version: 0.2
Summary: Javascript's Prototyping OO for Python
Home-page: http://tech.jonathangardner.net/wiki/Python-Prototype
Author: Jonathan Gardner
Author-email: jgardner@jonathangardner.net
License: Public Domain
Keywords: prototype javascript
Platform: UNKNOWN
Classifier: Development Status :: 4 - Beta
Classifier: Intended Audience :: Developers
Classifier: License :: Public Domain
Classifier: Programming Language :: JavaScript
